MANIFEST.in
README.md
VERSION
requirements.txt
setup.cfg
setup.py
bin/mongoke
mongoke/__init__.py
mongoke/__main__.py
mongoke/checksum.py
mongoke/config_schema.json
mongoke/constants.py
mongoke/generate_from_config.py
mongoke/generators.py
mongoke/graphql_support.py
mongoke/main.py
mongoke/naming.py
mongoke/support.py
mongoke.egg-info/PKG-INFO
mongoke.egg-info/SOURCES.txt
mongoke.egg-info/dependency_links.txt
mongoke.egg-info/requires.txt
mongoke.egg-info/top_level.txt
mongoke/templates/__init__.py
mongoke/templates/engine.py
mongoke/templates/graphql_query.py
mongoke/templates/jwt_middleware.py
mongoke/templates/logger.py
mongoke/templates/make_app.py
mongoke/templates/resolvers.py
mongoke/templates/resolvers_support.py
mongoke/templates/scalars.py
mongoke/templates/support.py